[
  {
    "idItem": "ITM-000001",
    "idProduct": "PRD-000002",
    "sku": "BTK-SL-M",
    "stock": 15,
    "price": 150000.0,
    "isActive": true
  },

  {
    "idItem": "ITM-000002",
    "idProduct": "PRD-000002",
    "sku": "BTK-SL-L",
    "stock": 10,
    "price": 160000.0,
    "isActive": true
  },

  {
    "idItem": "ITM-000003",
    "idProduct": "PRD-000002",
    "sku": "BTK-SL-XL",
    "stock": 5,
    "price": 175000.0,
    "isActive": true
  },

  {
    "idItem": "ITM-000004",
    "idProduct": "PRD-000009",
    "sku": "JKT-TNN-S",
    "stock": 8,
    "price": 325000.0,
    "isActive": true
  },

  {
    "idItem": "ITM-000005",
    "idProduct": "PRD-000009",
    "sku": "JKT-TNN-M",
    "stock": 12,
    "price": 350000.0,
    "isActive": true
  },

  {
    "idItem": "ITM-000006",
    "idProduct": "PRD-000007",
    "sku": "KRP-TMP-200G",
    "stock": 100,
    "price": 25000.0,
    "isActive": true
  },

  {
    "idItem": "ITM-000007",
    "idProduct": "PRD-000007",
    "sku": "KRP-TMP-500G",
    "stock": 50,
    "price": 55000.0,
    "isActive": true
  },

  {
    "idItem": "ITM-000008",
    "idProduct": "PRD-000010",
    "sku": "RDN-BDE-ORI",
    "stock": 20,
    "price": 85000.0,
    "isActive": true
  },

  {
    "idItem": "ITM-000009",
    "idProduct": "PRD-000010",
    "sku": "RDN-BDE-PDS",
    "stock": 15,
    "price": 90000.0,
    "isActive": true
  },

  {
    "idItem": "ITM-000010",
    "idProduct": "PRD-000001",
    "sku": "VAS-RTN-NAT",
    "stock": 25,
    "price": 125000.0,
    "isActive": true
  }
]